{
  "_fv": 24,
  "_type": "livingentity",
  "definition": {
    "mobName": "Jizzard",
    "mobLabel": "",
    "mobModelName": "Villager",
    "mobModelTexture": "imported_piskel_-_2021-12-21t025739.270.png",
    "mobModelGlowTexture": "",
    "modelWidth": 0.6,
    "modelHeight": 1.95,
    "modelShadowSize": 0.5,
    "mountedYOffset": 0.0,
    "hasSpawnEgg": true,
    "spawnEggBaseColor": {
      "value": -10092289,
      "falpha": 0.0
    },
    "spawnEggDotColor": {
      "value": -1,
      "falpha": 0.0
    },
    "creativeTab": {
      "value": "MISC"
    },
    "isBoss": true,
    "bossBarColor": "WHITE",
    "bossBarType": "PROGRESS",
    "equipmentMainHand": {
      "value": ""
    },
    "equipmentOffHand": {
      "value": ""
    },
    "equipmentHelmet": {
      "value": ""
    },
    "equipmentBody": {
      "value": ""
    },
    "equipmentLeggings": {
      "value": ""
    },
    "equipmentBoots": {
      "value": ""
    },
    "mobBehaviourType": "Mob",
    "mobCreatureType": "UNDEFINED",
    "attackStrength": 10,
    "attackKnockback": 1.0,
    "knockbackResistance": 0.5,
    "movementSpeed": 0.4,
    "armorBaseValue": 2.5,
    "trackingRange": 30,
    "health": 300,
    "xpAmount": 700,
    "waterMob": false,
    "flyingMob": false,
    "guiBoundTo": "<NONE>",
    "inventorySize": 9,
    "inventoryStackSize": 64,
    "disableCollisions": false,
    "ridable": false,
    "canControlForward": false,
    "canControlStrafe": false,
    "immuneToFire": false,
    "immuneToArrows": false,
    "immuneToFallDamage": false,
    "immuneToCactus": false,
    "immuneToDrowning": false,
    "immuneToLightning": false,
    "immuneToPotions": false,
    "immuneToPlayer": false,
    "immuneToExplosion": false,
    "immuneToTrident": false,
    "immuneToAnvil": false,
    "immuneToWither": false,
    "immuneToDragonBreath": false,
    "mobDrop": {
      "value": ""
    },
    "livingSound": {
      "value": "CUSTOM:jizzardambient"
    },
    "hurtSound": {
      "value": "CUSTOM:jizzardhurt1"
    },
    "deathSound": {
      "value": "CUSTOM:jizzarddeath"
    },
    "stepSound": {
      "value": "entity.zombie_villager.step"
    },
    "spawnParticles": false,
    "particleToSpawn": {
      "value": "DRAGON_BREATH"
    },
    "particleSpawningShape": "Spread",
    "particleSpawningRadious": 0.5,
    "particleAmount": 1,
    "hasAI": true,
    "aiBase": "(none)",
    "aixml": "<xml xmlns=\"https://developers.google.com/blockly/xml\"><block type=\"attack_entity\" x=\"16\" y=\"8\"><field name=\"insight\">FALSE</field><field name=\"nearby\">FALSE</field><field name=\"entity\">CUSTOM:Entity1</field><field name=\"condition\">null,null</field></block><block type=\"aitasks_container\" deletable=\"false\" x=\"40\" y=\"40\"><next><block type=\"attack_on_collide\"><field name=\"speed\">1.2</field><field name=\"longmemory\">FALSE</field><field name=\"condition\">null,null</field><next><block type=\"wander\"><field name=\"speed\">0</field><field name=\"condition\">null,null</field><next><block type=\"attack_action\"><field name=\"callhelp\">TRUE</field><field name=\"condition\">null,null</field><next><block type=\"look_around\"><field name=\"condition\">null,null</field><next><block type=\"swim_in_water\"><field name=\"condition\">null,null</field></block></next></block></next></block></next></block></next></block></next></block></xml>",
    "breedable": false,
    "tameable": false,
    "breedTriggerItems": [],
    "ranged": false,
    "rangedAttackItem": {
      "value": ""
    },
    "rangedItemType": "Default item",
    "spawnThisMob": true,
    "doesDespawnWhenIdle": false,
    "spawningProbability": 1,
    "mobSpawningType": "creature",
    "minNumberOfMobsPerGroup": 1,
    "maxNumberOfMobsPerGroup": 1,
    "restrictionBiomes": [
      {
        "value": "CUSTOM:GARBAGEDUMP"
      }
    ],
    "spawnInDungeons": false
  }
}